<?xml version='1.0' encoding='UTF-8'?>

<!-- =========== FULL CONFIGURATION FILE ================================== -->

<faces-config version="2.1"
              xmlns="http://java.sun.com/xml/ns/javaee"
              xmlns:xsi="http://www.w3.org/2001/XMLSchema-instance"
              xsi:schemaLocation="http://java.sun.com/xml/ns/javaee http://java.sun.com/xml/ns/javaee/web-facesconfig_2_1.xsd">


    <navigation-rule>
        <from-view-id>userLogin.xhtml</from-view-id>
        <navigation-case>
            <from-outcome>success</from-outcome>
            <to-view-id>MainPage.xhtml</to-view-id>
            <redirect/>
        </navigation-case>
        <navigation-case>
            <from-outcome>false</from-outcome>
            <to-view-id>userLogin.xhtml</to-view-id>
        </navigation-case>
    </navigation-rule>
     <navigation-rule>
        <from-view-id>userRegistration.xhtml</from-view-id>
        <navigation-case>
            <from-outcome>success</from-outcome>
            <to-view-id>userLogin.xhtml</to-view-id>
            <redirect/>
        </navigation-case>
        <navigation-case>
            <from-outcome>faile</from-outcome>
            <to-view-id>Registration.xhtml</to-view-id>
        </navigation-case>
    </navigation-rule>
    
</faces-config>
